caraml_auth/__init__.py
caraml_auth/id_token_credentials.py
tests/__init__.py
tests/test_id_token_credentials.py
caraml_auth_google-0.0.0.post9.dist-info/METADATA
caraml_auth_google-0.0.0.post9.dist-info/WHEEL
caraml_auth_google-0.0.0.post9.dist-info/top_level.txt
caraml_auth_google-0.0.0.post9.dist-info/RECORD
